alehundred_depot_es/__init__.py
alehundred_depot_es/main.py
alehundred_depot_es/p4_manager.py
alehundred_depot_es/tui.py
alehundred_depot_es/tui_help.py
alehundred_depot_es/tui_restart.py
alehundred_depot_es/tui_status.py
alehundred_depot_es/tui_user.py
alehundred_depot_es/utils.py
alehundred_depot_es-9.2.dist-info/licenses/LICENSE
alehundred_depot_es-9.2.dist-info/METADATA
alehundred_depot_es-9.2.dist-info/WHEEL
alehundred_depot_es-9.2.dist-info/entry_points.txt
alehundred_depot_es-9.2.dist-info/top_level.txt
alehundred_depot_es-9.2.dist-info/RECORD
