Metadata-Version: 2.4
Name: alehundred-depot-es
Version: 9.2
Summary: Herramienta TUI para instalar y gestionar un servidor Perforce en una Raspberry Pi.
Author-email: Alejandro Friant <friant2021@gmail.com>
License: Copyright (c) 2025 Alejandro Friant
Project-URL: Homepage, https://github.com/alefriant/Alehundred-VCS-Toolkit/tree/spanish
Project-URL: Bug Tracker, https://github.com/alefriant/Alehundred-VCS-Toolkit/issues
Classifier: Programming Language :: Python :: 3
Classifier: License :: OSI Approved :: MIT License
Classifier: Operating System :: POSIX :: Linux
Classifier: Environment :: Console :: Curses
Classifier: Topic :: Software Development :: Version Control
Classifier: Topic :: System :: Installation/Setup
Requires-Python: >=3.7
License-File: LICENSE
Requires-Dist: requests
Dynamic: license-file
